pyKirara/__init__.py
pyKirara/card.py
pyKirara/client.py
pyKirara/enums.py
pyKirara/errors.py
pyKirara/idol.py
pyKirara/infos.py
pyKirara/skills.py
pyKirara-1.2.0.dist-info/LICENSE
pyKirara-1.2.0.dist-info/METADATA
pyKirara-1.2.0.dist-info/WHEEL
pyKirara-1.2.0.dist-info/top_level.txt
pyKirara-1.2.0.dist-info/RECORD
