Metadata-Version: 2.1
Name: pyKirara
Version: 1.2.0
Summary: a Python wrapper for the starlight.kirara API
Home-page: https://github.com/EthanSk13s/pyKirara
Author: EthanSk13s
License: MIT
Project-URL: Documentation, https://pykirara.readthedocs.io/
Platform: UNKNOWN
Classifier: Development Status :: 5 - Production/Stable
Classifier: License :: OSI Approved :: MIT License
Classifier: Intended Audience :: Developers
Classifier: Natural Language :: English
Classifier: Operating System :: OS Independent
Classifier: Programming Language :: Python :: 3.5
Classifier: Programming Language :: Python :: 3.6
Classifier: Programming Language :: Python :: 3.7
Classifier: Topic :: Internet
Classifier: Topic :: Software Development :: Libraries
Classifier: Topic :: Software Development :: Libraries :: Python Modules
Classifier: Topic :: Utilities
Requires-Python: >=3.5
Requires-Dist: requests (>=2.21.0)
